{"delaysByInsurance":[["COVERED_BY_HEALTH_INSURANCE","39","34","115","50","26"],["NOT_COVERED_BY_HEALTH_INSURANCE","60","72","242","91","35"]],"delaysByRace":[["AFRICAN_AMERICAN","43","39","133","57","26"],["WHITE","41","41","127","48","29"]],"incidenceByStage":[["STAGE_4",2,1],["STAGE_1",28,43,58,26,16],["STAGE_3",11,11,6,11,4],["STAGE_2",31,16,20,26,18]],"incidenceByYear":[["incidence",72,70,85,63,38]],"incidenceByRace":[["WHITE",12,12,17,14,11],["AFRICAN_AMERICAN",23,33,55,35,15]],"incidenceByGender":[["MALE",40,32,44,29,21],["FEMALE",32,38,41,34,17]],"incidenceByAge":[["MALE",0,0,0,0,0,0,0,0.024950099800399198,0.10685187658608253,0.0564652738565782,0.3951944356623459,0.688259109311741,0.7969151670951157,0.572116832279434,0.6095604748155278,0.46656298600311047,0.3865267807840972,0.20942408376963353],["FEMALE",0,0,0,0,0,0,0,0,0.053425938293041264,0.0564652738565782,0.3951944356623459,0.5263157894736842,0.7969151670951157,0.36133694670280037,0.769971126082772,0.38880248833592534,0.44174489232468256,0.9424083769633508]],"polypRemoval":[["Polyps",141,126,160,119,96]],"mortality":[["Total",24,21,16,13,10]],"mortalityByGender":[["MALE",15,12,13,8,5],["FEMALE",9,9,3,5,5]],"mortalityByReason":[["Died from cancer",22,17,12,10,6],["Failed Treatment",2,4,4,3,4]],"mortalityByRace":[["AFRICAN_AMERICAN",12,10,8,9,5],["WHITE",3,3,1],["ASIAN",3,3,2],["AMERICAN_INDIAN",5,7,5,1,3]],"survivorByYear":[["survivors",144,127,160,123,99]],"_screeningByRace":[["AFRICAN_AMERICAN",17818],["WHITE",9337],["TWO_OR_MORE_RACES",858],["AMERICAN_INDIAN",114],["ASIAN",766],["SOME_OTHER_RACE",988],["NATIVE_HAWAIIAN",19]],"_screeningByHealthInsurance":[["COVERED_BY_HEALTH_INSURANCE",26122],["NOT_COVERED_BY_HEALTH_INSURANCE",3778]],"survivorByStage":[["STAGE_1",165],["STAGE_2",102],["STAGE_3",45],["STAGE_4",2]],"survivorByStageAndRace":[["WHITE",101,14,49,5],["AFRICAN_AMERICAN",224,39,100,12]]}