{"delaysByInsurance":[["COVERED_BY_HEALTH_INSURANCE","41","29","106","44","21"],["NOT_COVERED_BY_HEALTH_INSURANCE","54","62","241","72","38"]],"delaysByRace":[["AFRICAN_AMERICAN","40","31","119","41","23"],["WHITE","50","41","137","63","22"]],"incidenceByStage":[["STAGE_4",4,1],["STAGE_1",28,30,58,20,19],["STAGE_3",10,7,8,9,6],["STAGE_2",34,8,27,22,26]],"incidenceByYear":[["incidence",76,45,93,51,52]],"incidenceByRace":[["WHITE",5,9,20,14,13],["AFRICAN_AMERICAN",26,24,56,23,29]],"incidenceByGender":[["MALE",43,19,42,32,26],["FEMALE",33,26,51,19,26]],"incidenceByAge":[["MALE",0,0,0,0,0,0,0,0.024950099800399198,0.10685187658608253,0.0564652738565782,0.37938665823585205,0.6680161943319839,0.7455012853470437,0.4215597711532671,0.769971126082772,0.46656298600311047,0.3865267807840972,0.31413612565445026],["FEMALE",0,0,0,0,0,0,0,0,0.053425938293041264,0.0564652738565782,0.49004110022130887,0.44534412955465585,0.7455012853470437,0.331225534477567,0.6095604748155278,0.3499222395023328,0.6626173384870238,0.6282722513089005]],"polypRemoval":[["Polyps",119,95,127,85,85]],"mortality":[["Total",28,19,19,19,13]],"mortalityByGender":[["MALE",15,11,10,13,9],["FEMALE",13,8,9,6,4]],"mortalityByReason":[["Died from cancer",20,17,11,12,11],["Failed Treatment",8,2,8,7,2]],"mortalityByRace":[["AFRICAN_AMERICAN",16,6,6,13,3],["WHITE",3,3,2],["ASIAN",3,3,3,4,1],["AMERICAN_INDIAN",5,9,5,5]],"survivorByYear":[["survivors",121,95,130,86,89]],"_screeningByRace":[["AFRICAN_AMERICAN",17996],["WHITE",9243],["TWO_OR_MORE_RACES",870],["AMERICAN_INDIAN",104],["ASIAN",809],["SOME_OTHER_RACE",1054],["NATIVE_HAWAIIAN",21]],"_screeningByHealthInsurance":[["COVERED_BY_HEALTH_INSURANCE",26391],["NOT_COVERED_BY_HEALTH_INSURANCE",3706]],"survivorByStage":[["STAGE_1",138],["STAGE_2",91],["STAGE_3",34],["STAGE_4",3]],"survivorByStageAndRace":[["WHITE",83,37,17,4],["AFRICAN_AMERICAN",167,81,47,3,8]]}